{"cameraMode":{"drawMode":0,"name":"Shaded","section":"Shading Mode"},"sceneLighting":true,"audioPlay":false,"sceneViewState":{"m_AlwaysRefresh":false,"showFog":true,"showSkybox":true,"showFlares":true,"showImageEffects":true,"showParticleSystems":true,"showVisualEffectGraphs":true,"m_FxEnabled":true},"in2DMode":false,"pivot":{"x":1.0684270858764649,"y":9.475417137145996,"z":-8.27640151977539},"rotation":{"x":0.12596718966960908,"y":0.5047677755355835,"z":-0.07474003732204437,"w":0.8507382869720459},"size":181.3440399169922,"orthographic":false}